list_packages/__init__.py
list_packages/main.py
list_packages-1.0.8.dist-info/LICENSE
list_packages-1.0.8.dist-info/METADATA
list_packages-1.0.8.dist-info/WHEEL
list_packages-1.0.8.dist-info/entry_points.txt
list_packages-1.0.8.dist-info/top_level.txt
list_packages-1.0.8.dist-info/RECORD
