Metadata-Version: 2.1
Name: list_packages
Version: 1.0.8
Summary: A package to list all the installed Python packages and their dependencies
Home-page: https://github.com/maurya-anand/py-list-packages
Author: Anand Maurya
Author-email: anandmaurya@hotmail.com
License: MIT
Platform: Any
Classifier: License :: OSI Approved :: MIT License
Classifier: Programming Language :: Python
Classifier: Programming Language :: Python :: 3
Classifier: Programming Language :: Python :: 3.7
Classifier: Programming Language :: Python :: 3.8
Classifier: Programming Language :: Python :: 3.9
Classifier: Operating System :: OS Independent
License-File: LICENSE
